{
    "deviceName": "OCTAVE",
    "themeSetting": "CosmicVoyager",
    "startUpVolume": 0.21,
    "clockFormat24Hour": true,
    "showClock": true,
    "clockSize": 38,
    "backgroundGrid": "Normal",
    "screenWidth": 1920,
    "screenHeight": 1017,
    "backgroundBlurRadius": 15,
    "uiScale": 0.65,
    "obdParameters": {
        "COOLANT_TEMP": false,
        "CONTROL_MODULE_VOLTAGE": false,
        "ENGINE_LOAD": false,
        "THROTTLE_POS": false,
        "INTAKE_TEMP": true,
        "TIMING_ADVANCE": true,
        "MAF": true,
        "SPEED": false,
        "RPM": false,
        "COMMANDED_EQUIV_RATIO": true,
        "FUEL_LEVEL": true,
        "INTAKE_PRESSURE": true,
        "SHORT_FUEL_TRIM_1": true,
        "LONG_FUEL_TRIM_1": true,
        "O2_B1S1": true,
        "FUEL_PRESSURE": true,
        "OIL_TEMP": true,
        "FUEL_ECONOMY": true,
        "DISTANCE_TO_EMPTY": true,
        "IGNITION_TIMING": true
    },
    "obdBluetoothPort": "/dev/rfcomm0",
    "obdFastMode": true,
    "mediaFolder": "C:\\Users\\Robde\\Music\\The Great Outdoors",
    "showBackgroundOverlay": true,
    "fuelTankCapacity": 19.0,
    "directoryHistory": [
        "C:\\Users\\Redto\\Music",
        "C:\\Users\\Robde\\Music\\The Great Outdoors",
        "C:\\Users\\Robde\\Music\\Bangers & Mash"
    ],
    "homeOBDParameters": [],
    "customThemes": {},
    "bottomBarOrientation": "bottom"
}